[
{
  "fields": {
    "codename": "can_manage_executive_dashboard",
    "name": "Can manage executive dashboard",
    "content_type": 2
  },
  "model": "auth.permission",
  "pk": 1
},
{
  "fields": {
    "codename": "can_view_cell_lines",
    "name": "Can view cell lines",
    "content_type": 2
  },
  "model": "auth.permission",
  "pk": 2
},
{
  "fields": {
    "codename": "can_view_executive_dashboard",
    "name": "Can view executive dashboard",
    "content_type": 2
  },
  "model": "auth.permission",
  "pk": 3
},


{
  "fields": {
    "name": "Members",
    "permissions": [
      2
    ]
  },
  "model": "auth.group",
  "pk": 1
},
{
  "fields": {
    "name": "Executives",
    "permissions": [
      2,
      3
    ]
  },
  "model": "auth.group",
  "pk": 2
},
{
  "fields": {
    "name": "Executive administrators",
    "permissions": [
      1,
      2,
      3
    ]
  },
  "model": "auth.group",
  "pk": 3
},


{
  "fields": {
    "username": "joh@ebisc",
    "first_name": "Joh",
    "last_name": "Dokler",
    "is_active": true,
    "is_superuser": true,
    "is_staff": true,
    "last_login": "2015-04-10T10:16:49.628Z",
    "groups": [],
    "user_permissions": [],
    "password": "pbkdf2_sha256$15000$GjkUrBJ9Pj0G$eX/Fk/+MQXzc4m7279Tj3ygjb1ulgaBtZ8ycPbzqMls=",
    "email": "joh@douglasconnect.com",
    "date_joined": "2015-03-09T08:16:49Z"
  },
  "model": "auth.user",
  "pk": 1
},
{
  "fields": {
    "username": "maja@ebisc",
    "first_name": "Maja",
    "last_name": "Brajnik",
    "is_active": true,
    "is_superuser": true,
    "is_staff": true,
    "last_login": "2015-03-09T08:17:08Z",
    "groups": [],
    "user_permissions": [],
    "password": "pbkdf2_sha256$15000$HCCJWfNK8xCv$9g/tkPO8bxzl4sf2OumiREJ4ApjCwJ3MK4bl5r7MeC8=",
    "email": "maja@douglasconnect.com",
    "date_joined": "2015-03-09T08:17:08Z"
  },
  "model": "auth.user",
  "pk": 2
},
{
  "fields": {
    "username": "admin",
    "first_name": "",
    "last_name": "",
    "is_active": true,
    "is_superuser": false,
    "is_staff": true,
    "last_login": "2015-03-12T16:02:35.572Z",
    "groups": [],
    "user_permissions": [],
    "password": "pbkdf2_sha256$15000$e5R355l2lBCq$alsCbeze75/DT1g4yGtOuKl4b12307d65s7SjbJRy00=",
    "email": "",
    "date_joined": "2015-03-10T10:43:43Z"
  },
  "model": "auth.user",
  "pk": 3
}
]
